{"stats":{"minecraft:broken":{"minecraft:stone_pickaxe":1,"minecraft:stone_shovel":3},"minecraft:custom":{"minecraft:time_since_rest":17513,"minecraft:interact_with_furnace":3,"minecraft:sprint_one_cm":3383,"minecraft:damage_taken":250,"minecraft:walk_one_cm":80497,"minecraft:mob_kills":5,"minecraft:damage_dealt":839,"minecraft:interact_with_crafting_table":10,"minecraft:fly_one_cm":2774,"minecraft:open_chest":2,"minecraft:crouch_one_cm":10787,"minecraft:play_time":17513,"minecraft:sneak_time":3318,"minecraft:jump":146,"minecraft:leave_game":1,"minecraft:time_since_death":17513,"minecraft:total_world_time":17513,"minecraft:fall_one_cm":2363},"minecraft:killed":{"minecraft:zombie":4},"minecraft:used":{"minecraft:spruce_door":3,"minecraft:snow_block":64,"minecraft:stone_shovel":419,"minecraft:stone_pickaxe":131,"minecraft:chest":2,"minecraft:wooden_pickaxe":13,"minecraft:rotten_flesh":3,"minecraft:stone_axe":52,"minecraft:torch":3,"minecraft:dirt":5,"minecraft:cobblestone":6,"minecraft:crafting_table":2,"minecraft:furnace":1,"minecraft:cooked_porkchop":2,"minecraft:egg":4,"minecraft:snowball":49},"minecraft:crafted":{"minecraft:stone_shovel":3,"minecraft:spruce_planks":36,"minecraft:stick":16,"minecraft:wooden_pickaxe":1,"minecraft:stone_pickaxe":1,"minecraft:chest":1,"minecraft:snow_block":67,"minecraft:spruce_door":3,"minecraft:furnace":1,"minecraft:torch":16,"minecraft:stone_axe":1},"minecraft:picked_up":{"minecraft:crafting_table":2,"minecraft:cooked_porkchop":2,"minecraft:andesite":1,"minecraft:spruce_log":25,"minecraft:dirt":36,"minecraft:raw_copper":3,"minecraft:rotten_flesh":3,"minecraft:wheat_seeds":2,"minecraft:chest":1,"minecraft:coal":19,"minecraft:snowball":390,"minecraft:cobblestone":122,"minecraft:egg":4},"minecraft:mined":{"minecraft:large_fern":20,"minecraft:furnace":1,"minecraft:snow":388,"minecraft:spruce_log":25,"minecraft:andesite":1,"minecraft:crafting_table":2,"minecraft:short_grass":1,"minecraft:grass_block":9,"minecraft:coal_ore":19,"minecraft:chest":1,"minecraft:dirt":1,"minecraft:copper_ore":1,"minecraft:cobblestone":1,"minecraft:spruce_leaves":15,"minecraft:stone":121,"minecraft:fern":5}},"DataVersion":3955}